flexml/__init__.py
flexml/_feature_engineer.py
flexml/_model_tuner.py
flexml/classification.py
flexml/regression.py
flexml/config/__init__.py
flexml/config/ml_models.py
flexml/config/supervised_config.py
flexml/helpers/__init__.py
flexml/helpers/cross_validation.py
flexml/helpers/plot_model_graphs.py
flexml/helpers/supervised_helpers.py
flexml/helpers/tools.py
flexml/helpers/validators.py
flexml/logger/__init__.py
flexml/logger/logger.py
flexml/logs/__init__.py
flexml/structures/__init__.py
flexml/structures/supervised_base.py
flexml-1.1.0.dist-info/licenses/LICENSE
flexml-1.1.0.dist-info/METADATA
flexml-1.1.0.dist-info/WHEEL
flexml-1.1.0.dist-info/top_level.txt
flexml-1.1.0.dist-info/RECORD
