Metadata-Version: 2.4
Name: flexml
Version: 1.1.0
Summary: Easy-to-use and flexible AutoML library for Python
Author-email: Ozgur Aslan <ozguraslank@gmail.com>
License:                                  Apache License
Project-URL: Repository, https://github.com/ozguraslank/flexml
Project-URL: Issues, https://github.com/ozguraslank/flexml/issues
Keywords: AutoML,Machine Learning,Data Science,Regression,Classification
Classifier: Programming Language :: Python :: 3.9
Classifier: Programming Language :: Python :: 3.10
Classifier: Programming Language :: Python :: 3.11
Classifier: Programming Language :: Python :: 3.12
Classifier: Operating System :: OS Independent
Classifier: License :: OSI Approved :: Apache Software License
Requires-Python: <3.13,>=3.9
License-File: LICENSE
Requires-Dist: numpy<=1.26.4,>=1.21
Requires-Dist: pandas<2.2,>=2.0.1
Requires-Dist: scikit-learn<=1.5.2,>=1.5.0
Requires-Dist: xgboost<3.0.0,>=2.0.0
Requires-Dist: lightgbm>=4.0.0
Requires-Dist: catboost>=1.2.5
Requires-Dist: tqdm>=4.60.0
Requires-Dist: optuna>=3.0.0
Requires-Dist: ipython>=7.11.0
Requires-Dist: jinja2>=3.1.0
Requires-Dist: nbformat>=5.10.0
Requires-Dist: plotly>=6.0.0
Requires-Dist: yellowbrick>=1.5
Requires-Dist: shap>=0.46.0
Requires-Dist: rich>=13.9.0
Requires-Dist: setuptools; python_version >= "3.12"
Provides-Extra: test
Requires-Dist: pytest>=8.0.1; extra == "test"
Requires-Dist: parameterized>=0.8.1; extra == "test"
Requires-Dist: pytest-cov>=6.0.0; extra == "test"
Requires-Dist: seaborn>=0.13.0; extra == "test"
Dynamic: license-file
